aiarena21/__init__.py
aiarena21/client/__init__.py
aiarena21/client/classes.py
aiarena21/client/controller.py
aiarena21/client/data.py
aiarena21/client/input_source.py
aiarena21/client/random_source.py
aiarena21/client/runaway_source.py
aiarena21/server/__init__.py
aiarena21/server/controller.py
aiarena21/server/game.py
aiarena21/server/item.py
aiarena21/server/logs.py
aiarena21/server/network.py
aiarena21/server/player.py
aiarena21/server/settings.py
aiarena21/server/maps/1.txt
aiarena21/server/maps/2.txt
aiarena21/server/maps/3.txt
aiarena21/server/maps/4.txt
aiarena21/server/maps/5.txt
aiarena21/server/maps/6.txt
aiarena21/server/maps/7.txt
aiarena21/visual/__init__.py
aiarena21/visual/constants.py
aiarena21/visual/game.py
aiarena21/visual/game_input.py
aiarena21/visual/screen.py
aiarena21/visual/utils.py
aiarena21/visual/fonts/Montserrat/Montserrat-Black.ttf
aiarena21/visual/fonts/Montserrat/Montserrat-BlackItalic.ttf
aiarena21/visual/fonts/Montserrat/Montserrat-Bold.ttf
aiarena21/visual/fonts/Montserrat/Montserrat-BoldItalic.ttf
aiarena21/visual/fonts/Montserrat/Montserrat-ExtraBold.ttf
aiarena21/visual/fonts/Montserrat/Montserrat-ExtraBoldItalic.ttf
aiarena21/visual/fonts/Montserrat/Montserrat-ExtraLight.ttf
aiarena21/visual/fonts/Montserrat/Montserrat-ExtraLightItalic.ttf
aiarena21/visual/fonts/Montserrat/Montserrat-Italic.ttf
aiarena21/visual/fonts/Montserrat/Montserrat-Light.ttf
aiarena21/visual/fonts/Montserrat/Montserrat-LightItalic.ttf
aiarena21/visual/fonts/Montserrat/Montserrat-Medium.ttf
aiarena21/visual/fonts/Montserrat/Montserrat-MediumItalic.ttf
aiarena21/visual/fonts/Montserrat/Montserrat-Regular.ttf
aiarena21/visual/fonts/Montserrat/Montserrat-SemiBold.ttf
aiarena21/visual/fonts/Montserrat/Montserrat-SemiBoldItalic.ttf
aiarena21/visual/fonts/Montserrat/Montserrat-Thin.ttf
aiarena21/visual/fonts/Montserrat/Montserrat-ThinItalic.ttf
aiarena21/visual/fonts/Montserrat/OFL.txt
aiarena21/visual/sprites/food/DragonFruit.png
aiarena21-1.1.1.dist-info/LICENSE
aiarena21-1.1.1.dist-info/METADATA
aiarena21-1.1.1.dist-info/WHEEL
aiarena21-1.1.1.dist-info/entry_points.txt
aiarena21-1.1.1.dist-info/top_level.txt
aiarena21-1.1.1.dist-info/RECORD
